composio_claude_agent_sdk/__init__.py
composio_claude_agent_sdk/provider.py
composio_claude_agent_sdk/py.typed
tests/__init__.py
tests/test_provider.py
composio_claude_agent_sdk-0.10.7.dist-info/METADATA
composio_claude_agent_sdk-0.10.7.dist-info/WHEEL
composio_claude_agent_sdk-0.10.7.dist-info/top_level.txt
composio_claude_agent_sdk-0.10.7.dist-info/RECORD
