Metadata-Version: 2.4
Name: composio-claude-agent-sdk
Version: 0.10.7
Summary: Use Composio to get an array of tools with Claude Code Agents SDK.
Home-page: https://github.com/ComposioHQ/composio
Author: Composio
Author-email: Composio <tech@composio.dev>
Project-URL: Homepage, https://github.com/ComposioHQ/composio
Classifier: Programming Language :: Python :: 3
Classifier: License :: OSI Approved :: Apache Software License
Classifier: Operating System :: OS Independent
Requires-Python: >=3.10,<4
Requires-Dist: claude-agent-sdk>=0.1.0
Requires-Dist: composio
Dynamic: author
Dynamic: home-page
Dynamic: requires-python
